{
    "file_name": "",
    "data": [
        {
            "vi": "vì ai gây dựng cho nên nỗi này",
            "en": "By whose hand was this affliction wrought?"
        },
        {
            "vi": "sầu lên ngọn ải oán ra cửa phòng",
            "en": "Grief ascends the mountain pass, resentment spills from the chamber door."
        },
        {
            "vi": "lòng thiếp tựa bóng trăng theo dõi",
            "en": "My heart, like the moon's shadow, follows you."
        },
        {
            "vi": "quân đưa chàng ruổi lên đường",
            "en": "The troops escort the young lord on his journey."
        },
        {
            "vi": "đêm trăng này nghỉ mát phương đâủ",
            "en": "Upon this moonlit night, I find respite in distant lands."
        },
        {
            "vi": "xưa nay chiến địa dường bao",
            "en": "Throughout history, the battlefields have been countless."
        },
        {
            "vi": "nằm vùng cát trắng ngủ cồn rêu xanh",
            "en": "Reclining upon the white sands, slumbering amidst the verdant moss."
        },
        {
            "vi": "hình khe thế núi gần xa",
            "en": "The contours of ravines and mountains, near and far."
        },
        {
            "vi": "lên cao trông thức mây lồng",
            "en": "From heights I gaze, where clouds entwine and throng."
        },
        {
            "vi": "nay một thân nuôi già dạy trẻ",
            "en": "Now, I alone sustain the aged and nurture the young."
        },
        {
            "vi": "nguyệt lồng hoa hoa thắm từng bông",
            "en": "The moon embraces blossoms, each bloom a vibrant hue."
        },
        {
            "vi": "con chim bạt gió lạc loài kêu thương",
            "en": "A bird, lost and forlorn, cries out against the wind."
        },
        {
            "vi": "trông tư bề chân trời mặt đất",
            "en": "Gazing upon the boundless expanse of earth and sky."
        },
        {
            "vi": "lòng chàng có cũng như lòng thiếp chăng",
            "en": "Does your heart mirror mine, my lord?"
        },
        {
            "vi": "khi về đeo quả ấn vàng",
            "en": "Upon return, bearing the golden seal."
        }
    ]
}